SeTu/Core.py
SeTu/__init__.py
erispulse_setu-1.2.0.dist-info/entry_points.txt
erispulse_setu-1.2.0.dist-info/licenses/LICENSE
erispulse_setu-1.2.0.dist-info/WHEEL
erispulse_setu-1.2.0.dist-info/METADATA
erispulse_setu-1.2.0.dist-info/RECORD
