Metadata-Version: 2.4
Name: ErisPulse-SeTu
Version: 1.2.0
Summary: 简单的色图获取模块
Author-email: ShanFish <zcsfish@qq.com>
Requires-Python: >=3.9
License-File: LICENSE
Requires-Dist: aiohttp
Project-URL: homepage, https://github.com/shanfishapp/ErisPulse-SeTu
